ambipy_utils/__init__.py
ambipy_utils/clickup_service.py
ambipy_utils/email_sender.py
ambipy_utils/logger.py
ambipy_utils/postgres_handler.py
ambipy_utils/whatsapp_sender.py
ambipy_utils/helpers/enums.py
ambipy_utils/helpers/smtp_helper.py
ambipy_utils-0.2.2.dist-info/METADATA
ambipy_utils-0.2.2.dist-info/WHEEL
ambipy_utils-0.2.2.dist-info/entry_points.txt
ambipy_utils-0.2.2.dist-info/licenses/LICENSE
ambipy_utils-0.2.2.dist-info/RECORD
