Metadata-Version: 2.4
Name: ambipy-utils
Version: 0.2.2
Summary: Pacote interno da Ambipar Carbon para manipulação de dados geoespaciais, carbono e tabulares. Inclui suporte para conexão com bancos de dados, templates de e-mail e correção de dados
Author-email: GeoTech <geotech@ambipar.com>
License-File: LICENSE
Requires-Python: >=3.12
Requires-Dist: boto3>=1.40.33
Requires-Dist: geoalchemy2>=0.17.1
Requires-Dist: geopandas>=1.0.1
Requires-Dist: numpy>=2.2.4
Requires-Dist: pandas>=2.2.3
Requires-Dist: psycopg2>=2.9.10
Requires-Dist: requests>=2.32.3
Requires-Dist: shapely>=2.0.7
Requires-Dist: sqlalchemy>=2.0.39
